emissary/__init__.py
emissary/base.py
emissary-0.1.0a0.dist-info/LICENSE
emissary-0.1.0a0.dist-info/METADATA
emissary-0.1.0a0.dist-info/WHEEL
emissary-0.1.0a0.dist-info/top_level.txt
emissary-0.1.0a0.dist-info/RECORD
