Metadata-Version: 2.1
Name: emissary
Version: 0.1.0a0
Summary: A user-friendly way to interact with command line interfaces.
Author-email: "Jesse C. Sealand" <jesse.sealand@outlook.com>
License: MIT License
Project-URL: Homepage, https://github.com/jesse-sealand/emissary
Project-URL: Bug Tracker, https://github.com/jesse-sealand/emissary/issues
Keywords: python3,python,cli,cli wrapper
Classifier: Programming Language :: Python :: 3
Classifier: License :: OSI Approved :: MIT License
Classifier: Operating System :: OS Independent
Requires-Python: >=3.8
License-File: LICENSE
